pyjed/.pytest_cache/.gitignore
pyjed/.pytest_cache/CACHEDIR.TAG
pyjed/.pytest_cache/README.md
pyjed/.pytest_cache/v/cache/nodeids
pyjed/.pytest_cache/v/cache/stepwise
pyjed/__init__.py
pyjed/jcl.py
pyjed-0.1.0.dist-info/WHEEL
pyjed-0.1.0.dist-info/METADATA
pyjed-0.1.0.dist-info/RECORD
